cli_chat/__init__.py
cli_chat/app.py
cli_chat/bot.py
cli_chat/command.py
cli_chat/console.py
cli_chat-0.2.3.dist-info/LICENSE
cli_chat-0.2.3.dist-info/METADATA
cli_chat-0.2.3.dist-info/WHEEL
cli_chat-0.2.3.dist-info/entry_points.txt
cli_chat-0.2.3.dist-info/RECORD
