Metadata-Version: 2.1
Name: cli-chat
Version: 0.2.3
Summary: 
License: GPLv3
Author: Zhu Zhaomeng
Author-email: zhaomeng.zhu@ntu.edu.sg
Requires-Python: >=3.11,<4.0
Classifier: License :: Other/Proprietary License
Classifier: Programming Language :: Python :: 3
Classifier: Programming Language :: Python :: 3.11
Requires-Dist: appdirs (>=1.4.4,<2.0.0)
Requires-Dist: openai (>=0.27.0,<0.28.0)
Requires-Dist: prompt-toolkit (>=3.0.38,<4.0.0)
Requires-Dist: rich (>=13.3.1,<14.0.0)
Requires-Dist: typer (>=0.7.0,<0.8.0)
